irelease/__init__.py
irelease/examples.py
irelease/irelease.py
irelease-1.3.2.dist-info/licenses/LICENSE
irelease-1.3.2.dist-info/METADATA
irelease-1.3.2.dist-info/WHEEL
irelease-1.3.2.dist-info/entry_points.txt
irelease-1.3.2.dist-info/top_level.txt
irelease-1.3.2.dist-info/RECORD
