Metadata-Version: 2.4
Name: irelease
Version: 1.3.2
Summary: irelease is an Python package to release your package to Pypi.
Author-email: Erdogan Taskesen <erdogant@gmail.com>
License-Expression: MIT
Project-URL: Homepage, https://erdogant.github.io/irelease
Project-URL: Download, https://github.com/erdogant/irelease/archive/{version}.tar.gz
Keywords: Python,PyPI,release automation,package release,versioning,tagging,build automation,publishing,continuous integration,CI/CD,automation,release management
Classifier: Programming Language :: Python :: 3
Classifier: Operating System :: OS Independent
Classifier: Intended Audience :: Education
Classifier: Intended Audience :: Science/Research
Classifier: Operating System :: Unix
Classifier: Operating System :: Microsoft :: Windows
Classifier: Operating System :: MacOS
Classifier: Topic :: Scientific/Engineering :: Artificial Intelligence
Requires-Python: >=3
License-File: LICENSE
Requires-Dist: twine
Requires-Dist: packaging
Requires-Dist: numpy
Requires-Dist: toml
Requires-Dist: build
Dynamic: license-file
